pyrecursive/__init__.py
pyrecursive-0.0.2.dist-info/LICENSE
pyrecursive-0.0.2.dist-info/METADATA
pyrecursive-0.0.2.dist-info/WHEEL
pyrecursive-0.0.2.dist-info/top_level.txt
pyrecursive-0.0.2.dist-info/RECORD
