Metadata-Version: 2.1
Name: pyrecursive
Version: 0.0.2
Summary: Have you ever needed to transform a `whatever python object` in depth? So this one is for you. =]
Home-page: UNKNOWN
Author: Filipe Waitman
Author-email: filwaitman@gmail.com
License: MIT
Project-URL: Source, https://github.com/filwaitman/pyrecursive
Platform: UNKNOWN
Classifier: Development Status :: 1 - Planning
Classifier: Environment :: Web Environment
Classifier: Intended Audience :: Developers
Classifier: License :: OSI Approved :: MIT License
Classifier: Operating System :: OS Independent
Classifier: Programming Language :: Python
Classifier: Programming Language :: Python :: 2
Classifier: Programming Language :: Python :: 2.7
Classifier: Programming Language :: Python :: 3
Classifier: Programming Language :: Python :: 3.6
Classifier: Programming Language :: Python :: 3.7
Classifier: Programming Language :: Python :: 3.8
